[
  {
    "id": 1,
    "name": "CeSIUM Centro de Estudantes",
    "link": "https://cesium.di.uminho.pt/"
  },
  {
    "id": 2,
    "name": "GET BUS",
    "link": "https://www.getbus.eu/en/"
  },
  {
    "id": 3,
    "name": "marmela",
    "link": "https://marmelasoft.com/"
  },
  {
    "id": 4,
    "name": "Startup Braga",
    "link": "https://www.startupbraga.com/"
  },
  {
    "id": 5,
    "logo": "/",
    "link": ""
  },
  {
    "id": 6,
    "logo": "/",
    "link": ""
  },
  {
    "id": 7,
    "logo": "/",
    "link": ""
  },
  {
    "id": 8,
    "logo": "/",
    "link": ""
  },
  {
    "id": 9,
    "logo": "/",
    "link": ""
  }
]
